LICENSE.txt
siteplan/__init__.py
siteplan/app.py
siteplan/cli.py
siteplan/fe/js/lib.js
siteplan/fe/js/main.js
siteplan/fe/sass/app.css
siteplan/migrations/0001_initial.py
siteplan/migrations/__init__.py
siteplan/models.py
siteplan/myapp_templates/myapp/fe/js/lib.js
siteplan/myapp_templates/myapp/fe/js/main.js
siteplan/myapp_templates/myapp/fe/js/page/index.js
siteplan/myapp_templates/myapp/fe/sass/app.css
siteplan/myapp_templates/myapp/models.py
siteplan/myapp_templates/myapp/settings.py
siteplan/myapp_templates/myapp/urls.py
siteplan/myapp_templates/myapp/views.py
siteplan/myapp_templates/package.json
siteplan/myapp_templates/tailwind.config.js
siteplan/myapp_templates/webpack.mix.js
siteplan/server.py
siteplan/settings.py
siteplan/static/images/featured-small.jpg
siteplan/static/images/featured.jpg
siteplan/static/siteplan/css/app.css
siteplan/static/siteplan/css/input.css
siteplan/static/siteplan/js/lib.js
siteplan/static/siteplan/js/main.js
siteplan/templates/siteplan/base.html
siteplan/templates/siteplan/home_page.html
siteplan/urls.py
siteplan/views.py
siteplan-0.1.1.dist-info/LICENSE.txt
siteplan-0.1.1.dist-info/METADATA
siteplan-0.1.1.dist-info/WHEEL
siteplan-0.1.1.dist-info/entry_points.txt
siteplan-0.1.1.dist-info/RECORD
