Metadata-Version: 2.1
Name: siteplan
Version: 0.1.1
Summary: Quickly build django website
License: MIT
Author: Kamal Mustafa
Requires-Python: >=3.8,<4.0
Classifier: License :: OSI Approved :: MIT License
Classifier: Programming Language :: Python :: 3
Classifier: Programming Language :: Python :: 3.8
Classifier: Programming Language :: Python :: 3.9
Classifier: Programming Language :: Python :: 3.10
Classifier: Programming Language :: Python :: 3.11
Requires-Dist: Django (>=3.2.6,<4.0.0)
Requires-Dist: click (>=8.0.1,<9.0.0)
Requires-Dist: django-compressor (>=4.4,<5.0)
Requires-Dist: djangomix (>=1.1.3,<2.0.0)
Requires-Dist: gunicorn (>=20.1.0,<21.0.0)
Requires-Dist: wagtail (>=5.1.1,<6.0.0)
Requires-Dist: whitenoise (>=5.3.0,<6.0.0)
